tests/__init__.py
lc_classifier-2.0.3.dist-info/LICENSE
lc_classifier-2.0.3.dist-info/METADATA
lc_classifier-2.0.3.dist-info/WHEEL
lc_classifier-2.0.3.dist-info/top_level.txt
lc_classifier-2.0.3.dist-info/RECORD
